telegram_notifier_server.py
telegram_notifier_mcp_ac-0.1.1.dist-info/METADATA
telegram_notifier_mcp_ac-0.1.1.dist-info/WHEEL
telegram_notifier_mcp_ac-0.1.1.dist-info/top_level.txt
telegram_notifier_mcp_ac-0.1.1.dist-info/RECORD
